JLpyUtils/__init__.py
JLpyUtils/_plot_imgs.py
JLpyUtils/file_utils.py
JLpyUtils/git.py
JLpyUtils/img.py
JLpyUtils/kaggle.py
JLpyUtils/plot.py
JLpyUtils/summary_tables.py
JLpyUtils/video.py
JLpyUtils/ML/__init__.py
JLpyUtils/ML/_devices.py
JLpyUtils/ML/NeuralNet/Bert.py
JLpyUtils/ML/NeuralNet/Conv2D.py
JLpyUtils/ML/NeuralNet/Conv2D_AutoEncoder.py
JLpyUtils/ML/NeuralNet/DenseNet.py
JLpyUtils/ML/NeuralNet/__init__.py
JLpyUtils/ML/NeuralNet/_callbacks.py
JLpyUtils/ML/NeuralNet/_search.py
JLpyUtils/ML/NeuralNet/plot.py
JLpyUtils/ML/NeuralNet/search.py
JLpyUtils/ML/NeuralNet/utils.py
JLpyUtils/ML/dask_ml_extend/__init__.py
JLpyUtils/ML/dask_ml_extend/model_selection/__init__.py
JLpyUtils/ML/dask_ml_extend/model_selection/_search.py
JLpyUtils/ML/inspection/__init__.py
JLpyUtils/ML/inspection/_unique.py
JLpyUtils/ML/inspection/compare.py
JLpyUtils/ML/inspection/feature_importance.py
JLpyUtils/ML/inspection/maximize_success.py
JLpyUtils/ML/inspection/plot.py
JLpyUtils/ML/model_selection/__init__.py
JLpyUtils/ML/model_selection/_search.py
JLpyUtils/ML/model_selection/default_models_dict.py
JLpyUtils/ML/postprocessing/__init__.py
JLpyUtils/ML/postprocessing/transform.py
JLpyUtils/ML/preprocessing/Impute.py
JLpyUtils/ML/preprocessing/LabelEncode.py
JLpyUtils/ML/preprocessing/OneHotEncode.py
JLpyUtils/ML/preprocessing/Scale.py
JLpyUtils/ML/preprocessing/_CorrCoeff.py
JLpyUtils/ML/preprocessing/_PreprocessPipe.py
JLpyUtils/ML/preprocessing/__init__.py
JLpyUtils/ML/preprocessing/_feat_eng_pipe.py
JLpyUtils/ML/preprocessing/log.py
tests/ML/__init__.py
tests/ML/NeuralNet/__init__.py
tests/ML/NeuralNet/test_Bert.py
tests/ML/model_selection/__init__.py
tests/ML/model_selection/test_search.py
JLpyUtils-0.3.4.dist-info/LICENSE
JLpyUtils-0.3.4.dist-info/METADATA
JLpyUtils-0.3.4.dist-info/WHEEL
JLpyUtils-0.3.4.dist-info/top_level.txt
JLpyUtils-0.3.4.dist-info/RECORD
