Metadata-Version: 2.1
Name: JLpyUtils
Version: 0.3.4
Summary: General utilities to streamline data science and machine learning routines in python
Home-page: https://github.com/jlnerd/JLpyUtils.git
Author: John T. Leonard
Author-email: jtleona01@gmail.com
License: UNKNOWN
Platform: UNKNOWN
Requires-Dist: pytest
Requires-Dist: pytest-cov
Requires-Dist: codecov
Requires-Dist: gitpython
Requires-Dist: numpy
Requires-Dist: pandas
Requires-Dist: sklearn
Requires-Dist: scipy
Requires-Dist: matplotlib
Requires-Dist: tensorflow-gpu
Requires-Dist: tensorflow
Requires-Dist: torch
Requires-Dist: transformers
Requires-Dist: hyperopt
Requires-Dist: bson
Requires-Dist: kaggle
Requires-Dist: scikit-image
Requires-Dist: Pillow
Requires-Dist: opencv-python
Requires-Dist: nose
Requires-Dist: dill
Requires-Dist: h5py
Requires-Dist: dask
Requires-Dist: dask[dataframe]
Requires-Dist: fsspec (>=0.3.3)
Requires-Dist: dask-ml
Requires-Dist: dask-xgboost
Requires-Dist: xgboost
Requires-Dist: lightgbm
Requires-Dist: pydicom
